eeprivacy/__init__.py
eeprivacy/__version__.py
eeprivacy/mechanisms.py
eeprivacy/operations.py
eeprivacy-0.0.5.dist-info/LICENSE
eeprivacy-0.0.5.dist-info/METADATA
eeprivacy-0.0.5.dist-info/WHEEL
eeprivacy-0.0.5.dist-info/top_level.txt
eeprivacy-0.0.5.dist-info/RECORD
