Metadata-Version: 2.1
Name: eeprivacy
Version: 0.0.5
Summary: Energy Differential Privacy
Home-page: http://github.com/openeemeter/eeprivacy
Author: Marc Paré
Author-email: marc@recurve.com
License: UNKNOWN
Platform: UNKNOWN
Requires-Dist: click
Requires-Dist: pandas
Requires-Dist: scipy
